[
{"timestamp": "1510015285", "id": "f28ac211-53a4-4f30-b2b7-e594900554f7", "actions": [{"duration": 13229, "direction": "left"}, {"duration": 38747, "direction": "right"}, {"duration": 29951, "direction": "left"}, {"duration": 2515, "direction": "left"}, {"duration": 22559, "direction": "up"}, {"duration": 37074, "direction": "right"}, {"duration": 8339, "direction": "up"}], "ip": "22.213.31.148"},
{"timestamp": "1510015400", "id": "d2f0780b-48d6-4e6c-b1d1-926821414725", "actions": [{"duration": 29445, "direction": "right"}, {"duration": 42998, "direction": "right"}, {"duration": 42497, "direction": "left"}, {"duration": 13701, "direction": "right"}, {"duration": 20497, "direction": "idle"}, {"duration": 18534, "direction": "left"}, {"duration": 12689, "direction": "up"}, {"duration": 3320, "direction": "left"}, {"duration": 377, "direction": "left"}, {"duration": 10615, "direction": "idle"}, {"duration": 8845, "direction": "up"}, {"duration": 17905, "direction": "right"}, {"duration": 829, "direction": "up"}, {"duration": 34599, "direction": "right"}, {"duration": 19268, "direction": "left"}, {"duration": 31716, "direction": "up"}, {"duration": 5770, "direction": "right"}, {"duration": 44091, "direction": "down"}, {"duration": 28533, "direction": "right"}], "ip": "172.31.43.5"},
{"timestamp": "1510012958", "id": "9ab4afe6-04d4-4e7b-803d-bd18525c83a6", "actions": [{"duration": 5894, "direction": "down"}], "ip": "172.31.43.5"},
{"timestamp": "1510009909", "id": "0b9ca1e9-c78f-4b72-a8b9-f21d276cd01b", "actions": [{"duration": 18581, "direction": "right"}, {"duration": 10863, "direction": "left"}, {"duration": 23802, "direction": "down"}, {"duration": 38829, "direction": "up"}, {"duration": 33424, "direction": "right"}, {"duration": 43726, "direction": "right"}, {"duration": 18895, "direction": "down"}, {"duration": 33806, "direction": "idle"}, {"duration": 4314, "direction": "right"}, {"duration": 8685, "direction": "right"}, {"duration": 40826, "direction": "down"}, {"duration": 15246, "direction": "right"}, {"duration": 18673, "direction": "up"}, {"duration": 12459, "direction": "left"}, {"duration": 24336, "direction": "up"}], "ip": "172.31.43.5"},
{"timestamp": "1510011273", "id": "2976f32f-67b2-4dc0-8eac-bc162cc246d5", "actions": [{"duration": 5632, "direction": "right"}, {"duration": 40387, "direction": "right"}, {"duration": 19834, "direction": "right"}, {"duration": 8036, "direction": "idle"}, {"duration": 23802, "direction": "left"}, {"duration": 39872, "direction": "idle"}, {"duration": 44811, "direction": "idle"}, {"duration": 30576, "direction": "idle"}, {"duration": 36182, "direction": "left"}, {"duration": 30507, "direction": "up"}, {"duration": 37142, "direction": "right"}, {"duration": 32406, "direction": "left"}, {"duration": 42798, "direction": "right"}, {"duration": 17238, "direction": "down"}, {"duration": 19296, "direction": "right"}, {"duration": 13199, "direction": "up"}, {"duration": 7119, "direction": "up"}, {"duration": 3513, "direction": "right"}, {"duration": 9438, "direction": "left"}], "ip": "172.31.43.5"},
{"timestamp": "1510006376", "id": "2c5deef9-d165-4903-94bb-422dabbc8123", "actions": [{"duration": 7657, "direction": "left"}], "ip": "192.168.1.45"},
{"timestamp": "1510012789", "id": "52ad7bdb-cddb-4fdf-ae31-78e000ca3f77", "actions": [{"duration": 29462, "direction": "left"}, {"duration": 29970, "direction": "left"}, {"duration": 18710, "direction": "down"}, {"duration": 35188, "direction": "idle"}, {"duration": 7872, "direction": "left"}, {"duration": 26973, "direction": "left"}, {"duration": 15323, "direction": "right"}, {"duration": 28749, "direction": "left"}, {"duration": 43265, "direction": "up"}, {"duration": 30686, "direction": "right"}, {"duration": 45526, "direction": "idle"}, {"duration": 13180, "direction": "down"}, {"duration": 6180, "direction": "down"}, {"duration": 32571, "direction": "idle"}, {"duration": 39307, "direction": "right"}, {"duration": 14470, "direction": "right"}, {"duration": 6228, "direction": "right"}], "ip": "10.0.1.2"},
{"timestamp": "1510009841", "id": "8aad1644-44ce-4721-9c73-cb63f9a9a843", "actions": [{"duration": 42544, "direction": "up"}, {"duration": 18968, "direction": "idle"}, {"duration": 10290, "direction": "down"}, {"duration": 19217, "direction": "idle"}, {"duration": 21200, "direction": "idle"}, {"duration": 32240, "direction": "right"}, {"duration": 35229, "direction": "up"}, {"duration": 19971, "direction": "right"}, {"duration": 37745, "direction": "right"}, {"duration": 42597, "direction": "down"}, {"duration": 34246, "direction": "right"}, {"duration": 35093, "direction": "left"}, {"duration": 26557, "direction": "left"}, {"duration": 16463, "direction": "down"}, {"duration": 28912, "direction": "left"}, {"duration": 37862, "direction": "down"}, {"duration": 35537, "direction": "down"}, {"duration": 22128, "direction": "up"}, {"duration": 26813, "direction": "idle"}, {"duration": 4105, "direction": "down"}], "ip": "10.0.1.2"},
{"timestamp": "1510012862", "id": "694bf34a-8181-4995-ac23-ac618ed242d8", "actions": [{"duration": 34959, "direction": "left"}, {"duration": 28917, "direction": "up"}, {"duration": 35344, "direction": "idle"}, {"duration": 42677, "direction": "down"}, {"duration": 18464, "direction": "up"}, {"duration": 12548, "direction": "left"}, {"duration": 10080, "direction": "up"}, {"duration": 28566, "direction": "idle"}, {"duration": 43469, "direction": "up"}, {"duration": 30675, "direction": "up"}, {"duration": 2406, "direction": "down"}], "ip": "96.15.39.100"},
{"timestamp": "1510011771", "id": "eca26d8d-159f-4e41-9338-24df093a700b", "actions": [{"duration": 26278, "direction": "right"}, {"duration": 42656, "direction": "up"}, {"duration": 38176, "direction": "left"}, {"duration": 1404, "direction": "down"}, {"duration": 2355, "direction": "up"}, {"duration": 28178, "direction": "right"}, {"duration": 26183, "direction": "left"}, {"duration": 32753, "direction": "up"}, {"duration": 2837, "direction": "up"}, {"duration": 18829, "direction": "left"}], "ip": "24.78.105.90"},
{"timestamp": "1510015129", "id": "e55009cd-13f8-4cbc-be97-a9eeec03d2ce", "actions": [{"duration": 12750, "direction": "left"}, {"duration": 6034, "direction": "right"}, {"duration": 32993, "direction": "right"}, {"duration": 17443, "direction": "left"}, {"duration": 28788, "direction": "up"}, {"duration": 14377, "direction": "idle"}, {"duration": 30241, "direction": "idle"}, {"duration": 40429, "direction": "left"}, {"duration": 13633, "direction": "left"}, {"duration": 36108, "direction": "up"}, {"duration": 9099, "direction": "right"}, {"duration": 23956, "direction": "up"}], "ip": "127.0.0.1"},
{"timestamp": "1510015514", "id": "1473872b-0a9d-4398-b0dc-b1e4802a61f8", "actions": [{"duration": 26229, "direction": "idle"}, {"duration": 31752, "direction": "right"}, {"duration": 41641, "direction": "right"}, {"duration": 38063, "direction": "left"}, {"duration": 41609, "direction": "right"}, {"duration": 3486, "direction": "up"}, {"duration": 15472, "direction": "up"}, {"duration": 12996, "direction": "idle"}, {"duration": 24239, "direction": "down"}, {"duration": 38686, "direction": "right"}, {"duration": 41327, "direction": "up"}, {"duration": 41840, "direction": "down"}, {"duration": 30758, "direction": "left"}, {"duration": 27992, "direction": "idle"}], "ip": "83.246.97.145"},
{"timestamp": "1510011397", "id": "565f0c03-1d1a-4878-95da-b5f1c8fda135", "actions": [{"duration": 40072, "direction": "idle"}, {"duration": 32614, "direction": "right"}, {"duration": 12008, "direction": "idle"}, {"duration": 24737, "direction": "down"}, {"duration": 1256, "direction": "right"}, {"duration": 5453, "direction": "left"}, {"duration": 18013, "direction": "up"}, {"duration": 12626, "direction": "right"}], "ip": "96.15.39.100"},
{"timestamp": "1510009128", "id": "3da2baf0-7735-4f82-b658-6a2e73b31f6f", "actions": [{"duration": 24951, "direction": "up"}, {"duration": 2976, "direction": "idle"}, {"duration": 19988, "direction": "left"}, {"duration": 33168, "direction": "down"}, {"duration": 1661, "direction": "idle"}, {"duration": 28889, "direction": "left"}, {"duration": 34267, "direction": "down"}, {"duration": 44536, "direction": "left"}, {"duration": 37912, "direction": "down"}, {"duration": 24588, "direction": "up"}, {"duration": 22297, "direction": "left"}, {"duration": 33614, "direction": "down"}, {"duration": 6557, "direction": "idle"}, {"duration": 11936, "direction": "idle"}, {"duration": 11993, "direction": "idle"}, {"duration": 28854, "direction": "down"}, {"duration": 33283, "direction": "down"}], "ip": "10.0.1.2"},
{"timestamp": "1510012386", "id": "d14cf739-aea4-4be8-b1b2-f0848a5d5411", "actions": [{"duration": 31831, "direction": "down"}, {"duration": 22193, "direction": "up"}, {"duration": 16659, "direction": "down"}, {"duration": 35228, "direction": "left"}, {"duration": 37569, "direction": "up"}, {"duration": 33624, "direction": "idle"}, {"duration": 9483, "direction": "down"}, {"duration": 17370, "direction": "idle"}, {"duration": 25434, "direction": "up"}, {"duration": 44908, "direction": "up"}, {"duration": 12235, "direction": "up"}, {"duration": 42504, "direction": "up"}], "ip": "96.15.39.100"},
{"timestamp": "1510006708", "id": "1d8b8c29-2f90-4936-8d6a-b1fdf4334077", "actions": [{"duration": 20493, "direction": "up"}, {"duration": 8537, "direction": "down"}, {"duration": 24661, "direction": "down"}], "ip": "192.168.1.45"},
{"timestamp": "1510010822", "id": "8ab6fdeb-bd54-4707-b51a-8257a8ed9eff", "actions": [{"duration": 32840, "direction": "idle"}, {"duration": 2236, "direction": "right"}, {"duration": 44068, "direction": "idle"}, {"duration": 12979, "direction": "up"}, {"duration": 5133, "direction": "right"}, {"duration": 24443, "direction": "up"}, {"duration": 12995, "direction": "up"}], "ip": "22.213.31.148"},
{"timestamp": "1510009483", "id": "e208267b-5732-4398-bab0-eecb901619d2", "actions": [{"duration": 26786, "direction": "down"}, {"duration": 45291, "direction": "down"}, {"duration": 2846, "direction": "idle"}, {"duration": 4968, "direction": "right"}, {"duration": 11343, "direction": "down"}, {"duration": 33221, "direction": "idle"}, {"duration": 636, "direction": "idle"}, {"duration": 22129, "direction": "right"}, {"duration": 11199, "direction": "idle"}, {"duration": 14052, "direction": "left"}, {"duration": 29139, "direction": "left"}, {"duration": 15188, "direction": "up"}, {"duration": 20154, "direction": "idle"}, {"duration": 28437, "direction": "idle"}, {"duration": 36386, "direction": "idle"}, {"duration": 7256, "direction": "left"}, {"duration": 43492, "direction": "left"}, {"duration": 33401, "direction": "right"}, {"duration": 33523, "direction": "idle"}, {"duration": 11821, "direction": "idle"}], "ip": "83.246.97.145"},
{"timestamp": "1510012749", "id": "4c971df1-7575-4baf-b4b5-2c8898436f60", "actions": [{"duration": 31420, "direction": "up"}, {"duration": 17498, "direction": "up"}, {"duration": 43164, "direction": "right"}, {"duration": 40860, "direction": "down"}, {"duration": 32485, "direction": "left"}], "ip": "83.246.97.145"},
{"timestamp": "1510015130", "id": "88d4edb7-5349-40ec-93ba-7d81d2ba303f", "actions": [{"duration": 15105, "direction": "up"}], "ip": "192.168.1.45"},
{"timestamp": "1510011337", "id": "20e46af6-f58d-4126-9506-670ee2b4c59b", "actions": [{"duration": 25021, "direction": "idle"}, {"duration": 21373, "direction": "up"}], "ip": "22.213.31.148"},
{"timestamp": "1510015040", "id": "37d81fff-42d8-4177-b895-331e4f028772", "actions": [{"duration": 2998, "direction": "right"}, {"duration": 14548, "direction": "down"}, {"duration": 22229, "direction": "idle"}, {"duration": 7489, "direction": "left"}, {"duration": 24265, "direction": "up"}, {"duration": 6433, "direction": "left"}, {"duration": 38004, "direction": "up"}], "ip": "172.31.43.5"},
{"timestamp": "1510006277", "id": "3548048e-dea3-4a0b-85be-7185c7bd0df3", "actions": [{"duration": 3765, "direction": "left"}, {"duration": 32307, "direction": "left"}, {"duration": 7447, "direction": "idle"}, {"duration": 16198, "direction": "left"}, {"duration": 13055, "direction": "idle"}, {"duration": 4067, "direction": "left"}, {"duration": 3370, "direction": "down"}, {"duration": 27816, "direction": "up"}, {"duration": 15398, "direction": "right"}, {"duration": 24266, "direction": "down"}], "ip": "96.15.39.100"},
{"timestamp": "1510006172", "id": "707880d5-76f5-4082-b343-3f469cbcceda", "actions": [{"duration": 36416, "direction": "right"}, {"duration": 39425, "direction": "up"}, {"duration": 10465, "direction": "down"}, {"duration": 19785, "direction": "up"}, {"duration": 6618, "direction": "right"}, {"duration": 4301, "direction": "down"}, {"duration": 37032, "direction": "right"}, {"duration": 1835, "direction": "up"}, {"duration": 33684, "direction": "right"}, {"duration": 20135, "direction": "up"}, {"duration": 30560, "direction": "right"}, {"duration": 44479, "direction": "left"}, {"duration": 14897, "direction": "left"}, {"duration": 25779, "direction": "up"}, {"duration": 25768, "direction": "down"}, {"duration": 2606, "direction": "right"}], "ip": "24.78.105.90"},
{"timestamp": "1510006781", "id": "c1591ebb-187b-4664-b2af-7d3ad7831847", "actions": [{"duration": 2288, "direction": "idle"}, {"duration": 13069, "direction": "left"}, {"duration": 27260, "direction": "idle"}, {"duration": 3719, "direction": "idle"}, {"duration": 37484, "direction": "left"}, {"duration": 14970, "direction": "idle"}, {"duration": 12333, "direction": "up"}, {"duration": 43594, "direction": "left"}, {"duration": 787, "direction": "left"}, {"duration": 1360, "direction": "up"}, {"duration": 15104, "direction": "left"}, {"duration": 33846, "direction": "left"}], "ip": "96.15.39.100"},
{"timestamp": "1510014948", "id": "192e4ffa-d141-4c96-9a41-3054c3642ff6", "actions": [{"duration": 10943, "direction": "down"}, {"duration": 42933, "direction": "idle"}, {"duration": 37168, "direction": "up"}], "ip": "22.213.31.148"},
{"timestamp": "1510014043", "id": "4fcd32d7-a534-406f-80ac-4b81579df96b", "actions": [{"duration": 45663, "direction": "right"}, {"duration": 32651, "direction": "down"}, {"duration": 25163, "direction": "up"}, {"duration": 31136, "direction": "down"}, {"duration": 24976, "direction": "idle"}, {"duration": 27919, "direction": "down"}, {"duration": 23215, "direction": "left"}, {"duration": 20153, "direction": "up"}, {"duration": 21439, "direction": "up"}, {"duration": 24622, "direction": "right"}, {"duration": 43595, "direction": "left"}, {"duration": 18824, "direction": "up"}, {"duration": 28759, "direction": "right"}, {"duration": 9123, "direction": "down"}, {"duration": 38003, "direction": "up"}, {"duration": 27175, "direction": "idle"}, {"duration": 14795, "direction": "left"}, {"duration": 40718, "direction": "idle"}], "ip": "83.246.97.145"},
{"timestamp": "1510010695", "id": "db9bed91-691c-4868-b485-6da3689fd059", "actions": [{"duration": 26822, "direction": "idle"}, {"duration": 11699, "direction": "right"}, {"duration": 45351, "direction": "idle"}, {"duration": 32094, "direction": "up"}, {"duration": 16682, "direction": "idle"}, {"duration": 18120, "direction": "left"}, {"duration": 3277, "direction": "right"}, {"duration": 22783, "direction": "right"}, {"duration": 13833, "direction": "down"}, {"duration": 28791, "direction": "left"}, {"duration": 6216, "direction": "left"}, {"duration": 14544, "direction": "down"}, {"duration": 1870, "direction": "left"}, {"duration": 20865, "direction": "up"}, {"duration": 17451, "direction": "down"}], "ip": "24.78.105.90"},
{"timestamp": "1510007699", "id": "3e0b26cc-30e8-4f71-9e2c-94f975ec6b73", "actions": [{"duration": 14891, "direction": "left"}, {"duration": 24880, "direction": "up"}, {"duration": 19536, "direction": "left"}, {"duration": 42088, "direction": "left"}, {"duration": 41228, "direction": "right"}, {"duration": 18112, "direction": "idle"}, {"duration": 37555, "direction": "up"}, {"duration": 11430, "direction": "right"}, {"duration": 33535, "direction": "right"}, {"duration": 19795, "direction": "idle"}, {"duration": 27916, "direction": "right"}], "ip": "172.31.43.5"},
{"timestamp": "1510007994", "id": "0aa59b69-5d5b-4896-9022-145aec4af0bb", "actions": [{"duration": 646, "direction": "down"}, {"duration": 42088, "direction": "left"}, {"duration": 42825, "direction": "left"}, {"duration": 21967, "direction": "up"}, {"duration": 40464, "direction": "down"}, {"duration": 16872, "direction": "right"}, {"duration": 15478, "direction": "up"}, {"duration": 38064, "direction": "down"}, {"duration": 35314, "direction": "left"}, {"duration": 13819, "direction": "up"}, {"duration": 40639, "direction": "right"}, {"duration": 43437, "direction": "down"}, {"duration": 42759, "direction": "up"}, {"duration": 29528, "direction": "idle"}], "ip": "22.213.31.148"},
{"timestamp": "1510007672", "id": "798fa7cb-a8c9-4648-935a-7a2d04e43fc5", "actions": [{"duration": 22460, "direction": "left"}, {"duration": 25389, "direction": "right"}, {"duration": 12390, "direction": "left"}, {"duration": 6201, "direction": "down"}, {"duration": 17417, "direction": "left"}, {"duration": 12480, "direction": "idle"}, {"duration": 4783, "direction": "left"}, {"duration": 15092, "direction": "left"}], "ip": "192.168.1.45"},
{"timestamp": "1510015097", "id": "787860a0-9e86-46d6-b576-bf4e5fd2a639", "actions": [{"duration": 15283, "direction": "down"}, {"duration": 23286, "direction": "up"}, {"duration": 18968, "direction": "down"}, {"duration": 41091, "direction": "idle"}, {"duration": 39617, "direction": "right"}, {"duration": 5369, "direction": "left"}, {"duration": 23075, "direction": "down"}, {"duration": 20643, "direction": "down"}, {"duration": 13869, "direction": "idle"}, {"duration": 25735, "direction": "idle"}, {"duration": 35441, "direction": "right"}], "ip": "10.0.1.2"},
{"timestamp": "1510009372", "id": "c95ffc5d-75c8-4730-ae4e-0097b8de600c", "actions": [{"duration": 9951, "direction": "right"}, {"duration": 33833, "direction": "up"}, {"duration": 20032, "direction": "right"}, {"duration": 23583, "direction": "right"}, {"duration": 25691, "direction": "left"}, {"duration": 339, "direction": "left"}, {"duration": 31266, "direction": "left"}, {"duration": 16632, "direction": "left"}, {"duration": 40895, "direction": "idle"}, {"duration": 33896, "direction": "right"}, {"duration": 9595, "direction": "up"}, {"duration": 5401, "direction": "up"}, {"duration": 27738, "direction": "left"}, {"duration": 5434, "direction": "left"}, {"duration": 23325, "direction": "down"}, {"duration": 30153, "direction": "idle"}, {"duration": 43948, "direction": "right"}, {"duration": 36068, "direction": "idle"}, {"duration": 36465, "direction": "right"}], "ip": "96.15.39.100"},
{"timestamp": "1510011537", "id": "839382bf-edae-44ff-a7d2-594049cd8955", "actions": [{"duration": 41861, "direction": "right"}, {"duration": 14432, "direction": "up"}, {"duration": 1225, "direction": "left"}, {"duration": 36808, "direction": "right"}, {"duration": 30410, "direction": "down"}, {"duration": 34052, "direction": "right"}, {"duration": 18141, "direction": "idle"}, {"duration": 38490, "direction": "right"}, {"duration": 5861, "direction": "down"}, {"duration": 20831, "direction": "right"}, {"duration": 41988, "direction": "left"}, {"duration": 43763, "direction": "idle"}, {"duration": 42454, "direction": "idle"}, {"duration": 37124, "direction": "up"}, {"duration": 43858, "direction": "idle"}], "ip": "127.0.0.1"},
{"timestamp": "1510014636", "id": "2d5853c3-8a2e-4e8d-abd9-ee7c7d72bc51", "actions": [{"duration": 36671, "direction": "down"}, {"duration": 2862, "direction": "right"}, {"duration": 14032, "direction": "up"}, {"duration": 9524, "direction": "right"}, {"duration": 6929, "direction": "right"}, {"duration": 29243, "direction": "left"}, {"duration": 20241, "direction": "up"}, {"duration": 12748, "direction": "up"}, {"duration": 13178, "direction": "down"}, {"duration": 4693, "direction": "up"}, {"duration": 29856, "direction": "up"}, {"duration": 32176, "direction": "idle"}, {"duration": 39583, "direction": "down"}, {"duration": 30027, "direction": "up"}, {"duration": 39109, "direction": "up"}, {"duration": 7528, "direction": "left"}, {"duration": 1627, "direction": "idle"}, {"duration": 16549, "direction": "up"}, {"duration": 14299, "direction": "up"}], "ip": "96.15.39.100"},
{"timestamp": "1510009005", "id": "39652638-2315-4289-9842-167387f97030", "actions": [{"duration": 31041, "direction": "left"}, {"duration": 19407, "direction": "left"}, {"duration": 19994, "direction": "idle"}, {"duration": 3329, "direction": "up"}, {"duration": 12466, "direction": "left"}], "ip": "127.0.0.1"},
{"timestamp": "1510014517", "id": "5ceeb441-b420-4b9a-a50d-526df0ff32c2", "actions": [{"duration": 44132, "direction": "left"}, {"duration": 9939, "direction": "up"}, {"duration": 26927, "direction": "right"}, {"duration": 13844, "direction": "up"}, {"duration": 24435, "direction": "up"}, {"duration": 11269, "direction": "up"}, {"duration": 18063, "direction": "idle"}, {"duration": 40697, "direction": "left"}, {"duration": 36997, "direction": "idle"}, {"duration": 20681, "direction": "idle"}, {"duration": 18002, "direction": "up"}, {"duration": 3309, "direction": "left"}, {"duration": 11964, "direction": "right"}, {"duration": 5321, "direction": "up"}, {"duration": 24921, "direction": "idle"}, {"duration": 6225, "direction": "right"}, {"duration": 30209, "direction": "idle"}, {"duration": 21745, "direction": "up"}, {"duration": 41243, "direction": "down"}], "ip": "96.15.39.100"},
{"timestamp": "1510014196", "id": "0ba7e65f-7487-4387-b130-d1cb76f9f9ec", "actions": [{"duration": 1120, "direction": "right"}, {"duration": 16632, "direction": "idle"}, {"duration": 14860, "direction": "down"}, {"duration": 10137, "direction": "down"}, {"duration": 35013, "direction": "up"}, {"duration": 27762, "direction": "idle"}, {"duration": 30226, "direction": "up"}, {"duration": 8711, "direction": "right"}, {"duration": 22608, "direction": "down"}], "ip": "22.213.31.148"},
{"timestamp": "1510014023", "id": "3db30cdb-f5c0-40d3-a247-a425782096a9", "actions": [{"duration": 9494, "direction": "up"}, {"duration": 36365, "direction": "up"}, {"duration": 28330, "direction": "right"}, {"duration": 41835, "direction": "down"}, {"duration": 25816, "direction": "up"}, {"duration": 23034, "direction": "idle"}, {"duration": 25530, "direction": "down"}, {"duration": 31843, "direction": "down"}, {"duration": 35278, "direction": "idle"}, {"duration": 42185, "direction": "right"}], "ip": "172.31.43.5"},
{"timestamp": "1510010864", "id": "c08ba5da-0b30-47ce-a1be-d852bcd914cc", "actions": [{"duration": 26151, "direction": "down"}, {"duration": 2181, "direction": "idle"}, {"duration": 28322, "direction": "idle"}, {"duration": 6361, "direction": "idle"}, {"duration": 39322, "direction": "down"}, {"duration": 20893, "direction": "left"}, {"duration": 29146, "direction": "right"}, {"duration": 9857, "direction": "right"}, {"duration": 22649, "direction": "up"}, {"duration": 25472, "direction": "right"}, {"duration": 37196, "direction": "idle"}, {"duration": 41273, "direction": "up"}, {"duration": 15480, "direction": "up"}, {"duration": 6798, "direction": "left"}, {"duration": 1322, "direction": "idle"}, {"duration": 3348, "direction": "down"}, {"duration": 8297, "direction": "down"}, {"duration": 19929, "direction": "left"}, {"duration": 36184, "direction": "up"}, {"duration": 23263, "direction": "left"}], "ip": "83.246.97.145"},
{"timestamp": "1510015286", "id": "13572c68-d198-40ba-ba8a-7f93df4ad422", "actions": [{"duration": 30369, "direction": "right"}, {"duration": 41546, "direction": "left"}, {"duration": 21370, "direction": "right"}, {"duration": 39326, "direction": "idle"}, {"duration": 9572, "direction": "left"}], "ip": "10.0.1.2"},
{"timestamp": "1510010870", "id": "41e95dc7-675f-4dd0-90ed-17a96a99361b", "actions": [{"duration": 15797, "direction": "idle"}, {"duration": 33615, "direction": "up"}, {"duration": 4182, "direction": "left"}, {"duration": 7344, "direction": "left"}, {"duration": 13983, "direction": "up"}, {"duration": 1128, "direction": "up"}, {"duration": 24222, "direction": "idle"}, {"duration": 37741, "direction": "down"}, {"duration": 43251, "direction": "right"}, {"duration": 22292, "direction": "up"}, {"duration": 18543, "direction": "left"}, {"duration": 37974, "direction": "left"}, {"duration": 12799, "direction": "down"}, {"duration": 18200, "direction": "left"}, {"duration": 31542, "direction": "right"}, {"duration": 3838, "direction": "idle"}, {"duration": 36380, "direction": "up"}], "ip": "24.78.105.90"},
{"timestamp": "1510012066", "id": "04f6354b-8bbd-45a4-88ea-f5fa1825ba55", "actions": [{"duration": 25672, "direction": "idle"}, {"duration": 22673, "direction": "left"}, {"duration": 14663, "direction": "left"}, {"duration": 19622, "direction": "idle"}, {"duration": 7345, "direction": "up"}, {"duration": 16942, "direction": "left"}, {"duration": 18670, "direction": "up"}, {"duration": 43545, "direction": "down"}, {"duration": 8976, "direction": "right"}, {"duration": 16239, "direction": "up"}, {"duration": 26057, "direction": "down"}, {"duration": 38269, "direction": "up"}, {"duration": 9929, "direction": "down"}, {"duration": 28870, "direction": "right"}, {"duration": 2028, "direction": "up"}, {"duration": 24603, "direction": "idle"}, {"duration": 20576, "direction": "left"}, {"duration": 20579, "direction": "idle"}, {"duration": 15344, "direction": "idle"}, {"duration": 34252, "direction": "down"}], "ip": "96.15.39.100"},
{"timestamp": "1510014239", "id": "7470f0f5-ad51-48d7-a58f-96f9a001ffa6", "actions": [{"duration": 40304, "direction": "left"}, {"duration": 28893, "direction": "right"}, {"duration": 2054, "direction": "down"}, {"duration": 9776, "direction": "down"}, {"duration": 26243, "direction": "idle"}, {"duration": 8613, "direction": "up"}, {"duration": 8359, "direction": "right"}], "ip": "10.0.1.2"},
{"timestamp": "1510008216", "id": "535b47a0-ded9-43fc-b3a8-4a8a854c39e0", "actions": [{"duration": 32535, "direction": "up"}, {"duration": 38795, "direction": "idle"}, {"duration": 2564, "direction": "down"}, {"duration": 20947, "direction": "right"}, {"duration": 26463, "direction": "idle"}, {"duration": 32151, "direction": "right"}, {"duration": 44454, "direction": "left"}, {"duration": 40282, "direction": "left"}, {"duration": 26412, "direction": "up"}, {"duration": 20946, "direction": "idle"}, {"duration": 32580, "direction": "right"}, {"duration": 8028, "direction": "right"}, {"duration": 8107, "direction": "left"}, {"duration": 1737, "direction": "idle"}, {"duration": 31878, "direction": "down"}], "ip": "24.78.105.90"},
{"timestamp": "1510007906", "id": "d5a597d7-8d0b-4977-899e-9176956c0719", "actions": [{"duration": 21602, "direction": "up"}, {"duration": 18740, "direction": "up"}, {"duration": 2168, "direction": "left"}, {"duration": 40315, "direction": "up"}, {"duration": 39240, "direction": "right"}, {"duration": 5724, "direction": "up"}], "ip": "127.0.0.1"},
{"timestamp": "1510008623", "id": "3cdf3a8e-99d0-46bf-8b42-2b465d22e5ab", "actions": [{"duration": 7588, "direction": "left"}, {"duration": 22759, "direction": "idle"}, {"duration": 19181, "direction": "up"}, {"duration": 3163, "direction": "left"}, {"duration": 21048, "direction": "idle"}, {"duration": 12894, "direction": "up"}, {"duration": 37662, "direction": "idle"}, {"duration": 30310, "direction": "down"}], "ip": "24.78.105.90"},
{"timestamp": "1510006878", "id": "029ce773-88c6-4003-8772-dfadd8465611", "actions": [{"duration": 27655, "direction": "idle"}, {"duration": 8034, "direction": "up"}, {"duration": 37752, "direction": "right"}, {"duration": 20452, "direction": "left"}, {"duration": 34923, "direction": "up"}, {"duration": 16811, "direction": "down"}, {"duration": 28570, "direction": "down"}, {"duration": 35391, "direction": "down"}, {"duration": 38603, "direction": "up"}, {"duration": 15564, "direction": "right"}, {"duration": 36347, "direction": "idle"}], "ip": "96.15.39.100"},
{"timestamp": "1510010652", "id": "5872bbcb-f9d6-47d5-8ad1-b9cd7aafc1ee", "actions": [{"duration": 12513, "direction": "down"}, {"duration": 8435, "direction": "idle"}, {"duration": 7355, "direction": "right"}, {"duration": 6326, "direction": "left"}, {"duration": 41611, "direction": "left"}, {"duration": 41094, "direction": "left"}, {"duration": 44687, "direction": "down"}], "ip": "127.0.0.1"},
{"timestamp": "1510011525", "id": "06c8155c-e1e7-4ad1-8474-9d37f3179d29", "actions": [{"duration": 2563, "direction": "left"}, {"duration": 28919, "direction": "left"}, {"duration": 29597, "direction": "right"}, {"duration": 43754, "direction": "left"}, {"duration": 38005, "direction": "right"}, {"duration": 17009, "direction": "up"}, {"duration": 6608, "direction": "down"}], "ip": "192.168.1.45"},
{"timestamp": "1510014456", "id": "0cf621a2-613c-46df-be20-e45a089d81f1", "actions": [{"duration": 26390, "direction": "right"}, {"duration": 5328, "direction": "idle"}, {"duration": 25051, "direction": "left"}, {"duration": 44167, "direction": "down"}, {"duration": 24018, "direction": "up"}, {"duration": 14922, "direction": "left"}, {"duration": 39145, "direction": "up"}, {"duration": 20461, "direction": "up"}, {"duration": 31431, "direction": "idle"}, {"duration": 8714, "direction": "down"}, {"duration": 38809, "direction": "idle"}, {"duration": 16128, "direction": "down"}, {"duration": 30168, "direction": "down"}], "ip": "127.0.0.1"},
{"timestamp": "1510006308", "id": "69f4f100-a993-41f8-8470-c197c7409e3c", "actions": [{"duration": 24756, "direction": "idle"}, {"duration": 27196, "direction": "down"}, {"duration": 44907, "direction": "right"}, {"duration": 21525, "direction": "right"}, {"duration": 36985, "direction": "up"}, {"duration": 30396, "direction": "down"}, {"duration": 31743, "direction": "right"}], "ip": "192.168.1.45"},
{"timestamp": "1510007758", "id": "28d5a825-c976-484e-a1b6-9cf2cdd5d44f", "actions": [{"duration": 13040, "direction": "down"}, {"duration": 26940, "direction": "right"}, {"duration": 8831, "direction": "down"}, {"duration": 17638, "direction": "right"}, {"duration": 28170, "direction": "idle"}, {"duration": 17061, "direction": "idle"}, {"duration": 7667, "direction": "left"}, {"duration": 5541, "direction": "down"}, {"duration": 5587, "direction": "right"}, {"duration": 3044, "direction": "left"}, {"duration": 301, "direction": "down"}, {"duration": 41083, "direction": "left"}, {"duration": 31946, "direction": "idle"}, {"duration": 31436, "direction": "up"}, {"duration": 45673, "direction": "right"}], "ip": "127.0.0.1"},
{"timestamp": "1510007335", "id": "9fec2c87-5169-46d6-a97f-80905b7c7e58", "actions": [{"duration": 11527, "direction": "up"}, {"duration": 2060, "direction": "right"}], "ip": "83.246.97.145"},
{"timestamp": "1510008058", "id": "272fb1a3-bb52-451f-a6d8-db1f22de269e", "actions": [{"duration": 15403, "direction": "right"}, {"duration": 31869, "direction": "up"}, {"duration": 36598, "direction": "down"}, {"duration": 18354, "direction": "right"}, {"duration": 11168, "direction": "right"}, {"duration": 16235, "direction": "right"}, {"duration": 2650, "direction": "down"}, {"duration": 38771, "direction": "right"}, {"duration": 16261, "direction": "idle"}, {"duration": 8511, "direction": "left"}, {"duration": 37917, "direction": "up"}, {"duration": 22056, "direction": "right"}, {"duration": 37006, "direction": "up"}, {"duration": 20957, "direction": "left"}, {"duration": 18085, "direction": "up"}, {"duration": 36196, "direction": "idle"}, {"duration": 27798, "direction": "idle"}, {"duration": 569, "direction": "left"}, {"duration": 36210, "direction": "idle"}, {"duration": 37462, "direction": "down"}], "ip": "127.0.0.1"},
{"timestamp": "1510007818", "id": "e3a9b3e8-1104-4855-8cf4-d026ff2f6614", "actions": [{"duration": 42670, "direction": "left"}, {"duration": 34234, "direction": "left"}, {"duration": 6455, "direction": "idle"}, {"duration": 42457, "direction": "down"}], "ip": "96.15.39.100"},
{"timestamp": "1510011810", "id": "58a342e0-01d0-44c3-bc94-9347ce243618", "actions": [{"duration": 6230, "direction": "up"}, {"duration": 19705, "direction": "left"}, {"duration": 43090, "direction": "down"}, {"duration": 25108, "direction": "down"}, {"duration": 26281, "direction": "left"}, {"duration": 23877, "direction": "up"}, {"duration": 37680, "direction": "up"}, {"duration": 5762, "direction": "right"}, {"duration": 6600, "direction": "idle"}, {"duration": 2358, "direction": "left"}, {"duration": 45175, "direction": "left"}, {"duration": 41967, "direction": "right"}, {"duration": 17803, "direction": "right"}, {"duration": 11245, "direction": "right"}], "ip": "96.15.39.100"},
{"timestamp": "1510008261", "id": "cd2c30a9-b6ca-49a2-83dd-9a40b9398da8", "actions": [{"duration": 27958, "direction": "down"}, {"duration": 42469, "direction": "right"}, {"duration": 41586, "direction": "left"}, {"duration": 15939, "direction": "up"}, {"duration": 2099, "direction": "left"}, {"duration": 2131, "direction": "down"}, {"duration": 17072, "direction": "idle"}, {"duration": 205, "direction": "left"}, {"duration": 229, "direction": "down"}, {"duration": 15066, "direction": "right"}, {"duration": 40340, "direction": "left"}, {"duration": 41098, "direction": "down"}, {"duration": 25573, "direction": "left"}, {"duration": 42705, "direction": "idle"}, {"duration": 18660, "direction": "left"}], "ip": "22.213.31.148"},
{"timestamp": "1510009468", "id": "d9d041c5-5580-4fe0-afbb-1496385b0ca9", "actions": [{"duration": 41122, "direction": "up"}], "ip": "192.168.1.45"},
{"timestamp": "1510014606", "id": "516080f6-7a79-4415-8a61-b40c24173ba4", "actions": [{"duration": 30643, "direction": "down"}, {"duration": 22869, "direction": "down"}, {"duration": 27857, "direction": "right"}, {"duration": 261, "direction": "right"}], "ip": "22.213.31.148"},
{"timestamp": "1510014526", "id": "33173df3-9f13-478f-be0a-3a2cf5892b24", "actions": [{"duration": 38555, "direction": "up"}, {"duration": 4196, "direction": "down"}, {"duration": 17443, "direction": "up"}, {"duration": 23709, "direction": "up"}, {"duration": 30339, "direction": "idle"}, {"duration": 38055, "direction": "down"}, {"duration": 44282, "direction": "down"}, {"duration": 9183, "direction": "left"}, {"duration": 29617, "direction": "idle"}, {"duration": 33934, "direction": "idle"}, {"duration": 44858, "direction": "right"}, {"duration": 42258, "direction": "left"}, {"duration": 45070, "direction": "idle"}], "ip": "10.0.1.2"},
{"timestamp": "1510007329", "id": "14d96418-d89d-4642-ba89-95e8735de4af", "actions": [{"duration": 25051, "direction": "right"}, {"duration": 15231, "direction": "down"}, {"duration": 31467, "direction": "left"}, {"duration": 5869, "direction": "idle"}, {"duration": 10389, "direction": "down"}, {"duration": 14537, "direction": "left"}, {"duration": 36549, "direction": "down"}, {"duration": 6657, "direction": "down"}, {"duration": 31852, "direction": "right"}, {"duration": 11036, "direction": "up"}, {"duration": 6074, "direction": "down"}, {"duration": 34216, "direction": "right"}, {"duration": 32865, "direction": "down"}, {"duration": 40398, "direction": "idle"}, {"duration": 41927, "direction": "down"}, {"duration": 2259, "direction": "idle"}, {"duration": 7045, "direction": "up"}], "ip": "96.15.39.100"},
{"timestamp": "1510011091", "id": "c13cf09a-65c7-4a0f-805a-c728415985b0", "actions": [{"duration": 11973, "direction": "down"}, {"duration": 31608, "direction": "idle"}], "ip": "22.213.31.148"}]
